zdraw/__init__.py
zdraw/test.py
zdraw/usage_example.py
zdraw/zdraw.py
zdraw-0.1.3.8.dist-info/licenses/LICENSE
zdraw-0.1.3.8.dist-info/METADATA
zdraw-0.1.3.8.dist-info/WHEEL
zdraw-0.1.3.8.dist-info/top_level.txt
zdraw-0.1.3.8.dist-info/RECORD
