Metadata-Version: 2.4
Name: zdraw
Version: 0.1.3.8
Summary: A high-performance drawing library for AI vision tasks, bounding boxes, and keypoints.
Author: Zaid Aslam
Author-email: Zaid <zaidmughal46@gmail.com>
Project-URL: Homepage, https://github.com/MZaid101/zdraw
Project-URL: Bug Tracker, https://github.com/MZaid101/zdraw/issues
Classifier: Programming Language :: Python :: 3
Classifier: License :: OSI Approved :: MIT License
Classifier: Operating System :: OS Independent
Classifier: Topic :: Scientific/Engineering :: Artificial Intelligence
Requires-Python: >=3.8
License-File: LICENSE
Requires-Dist: numpy
Requires-Dist: opencv-python
Requires-Dist: pillow
Dynamic: author
Dynamic: license-file
Dynamic: requires-python
